wazzup/__init__.py
wazzup/messaging.py
wazzup/whatsapp.py
wazzup/models/__init__.py
wazzup/models/image_message.py
wazzup/models/location_message.py
wazzup/models/message_reaction.py
wazzup/models/template_componenets.py
wazzup/models/template_message.py
wazzup/models/template_parameters.py
wazzup/models/text_message.py
wazzup-0.0.2.dist-info/licenses/LICENCE
wazzup-0.0.2.dist-info/METADATA
wazzup-0.0.2.dist-info/WHEEL
wazzup-0.0.2.dist-info/top_level.txt
wazzup-0.0.2.dist-info/RECORD
